CiceroCoder/__init__.py
CiceroCoder/cifraCesar/__init__.py
CiceroCoder/cifraCesar/alphabet.py
CiceroCoder/cifraCesar/decode.py
CiceroCoder/cifraCesar/encode.py
CiceroCoder/module2_name/__init__.py
CiceroCoder/module2_name/file1_name.py
CiceroCoder/module2_name/file2_name.py
cicero_coder-0.0.1.dist-info/METADATA
cicero_coder-0.0.1.dist-info/WHEEL
cicero_coder-0.0.1.dist-info/top_level.txt
cicero_coder-0.0.1.dist-info/RECORD
