Metadata-Version: 2.1
Name: cicero-coder
Version: 0.0.1
Summary: Crypt and Decrypt words ans phrases by Caesar's Cipher
Home-page: https://github.com/CiceroHitzschky/Dio-DataScientistBootCamp/tree/master/DataScientist/Criando%20Pacotes%20e%20M%C3%B3dulos%20Python/cifracesar/CiceroCoder/cifraCesar
Author: Cícero Hitzschky
Author-email: 
Requires-Python: >=3.8
